samgis_web/__init__.py
samgis_web/__version__.py
samgis_web/io_package/__init__.py
samgis_web/io_package/coordinates_pixel_conversion.py
samgis_web/io_package/geo_helpers.py
samgis_web/io_package/raster_helpers.py
samgis_web/io_package/tms2geotiff.py
samgis_web/prediction_api/__init__.py
samgis_web/prediction_api/predictors.py
samgis_web/utilities/__init__.py
samgis_web/utilities/constants.py
samgis_web/utilities/local_tiles_http_server.py
samgis_web/utilities/type_hints.py
samgis_web/web/__init__.py
samgis_web/web/exception_handlers.py
samgis_web/web/gradio_helpers.py
samgis_web/web/middlewares.py
samgis_web/web/web_helpers.py
samgis_web-1.2.15.dist-info/METADATA
samgis_web-1.2.15.dist-info/WHEEL
samgis_web-1.2.15.dist-info/RECORD
