Metadata-Version: 2.3
Name: samgis_web
Version: 1.2.15
Summary: SamGIS WEB
License: MIT
Author: alessandro trinca tornidor
Author-email: alessandro@trinca.tornidor.com
Requires-Python: >=3.10,<3.13
Classifier: License :: OSI Approved :: MIT License
Classifier: Programming Language :: Python :: 3
Classifier: Programming Language :: Python :: 3.10
Classifier: Programming Language :: Python :: 3.11
Classifier: Programming Language :: Python :: 3.12
Requires-Dist: asgi-correlation-id (>=4.3.1,<5.0.0)
Requires-Dist: contextily (>=1.6.0,<2.0.0)
Requires-Dist: fastapi (>=0.128.0,<0.129.0)
Requires-Dist: geopandas (>=1.0.1,<2.0.0)
Requires-Dist: jinja2 (>=3.1.4,<4.0.0)
Requires-Dist: rasterio (>=1.3.10,<2.0.0)
Requires-Dist: requests (>=2.32.3,<3.0.0)
Requires-Dist: samgis-core (==3.4.2)
Requires-Dist: shapely (>=2.0.5,<3.0.0)
Requires-Dist: starlette (>=0.50.0,<0.51.0)
Requires-Dist: uvicorn (>=0.40.0,<0.41.0)
Project-URL: Source, https://gitlab.com/aletrn/samgis_web
